{
  "case": "PROMO_ADD_COMBO_003",
  "steps": [
    {
      "index": 1,
      "action": "navigate",
      "model": "",
      "phase": "预处理",
      "status": "ok",
      "return_source": "keyword_result",
      "return_value": true,
      "named_writes": {}
    },
    {
      "index": 2,
      "action": "wait",
      "model": "",
      "phase": "预处理",
      "status": "ok",
      "return_source": "keyword_result",
      "return_value": true,
      "named_writes": {}
    },
    {
      "index": 3,
      "action": "type",
      "model": "PassportLogin",
      "phase": "预处理",
      "status": "ok",
      "return_source": "keyword_result",
      "return_value": {
        "loginModePassword": "click",
        "username": "mandy",
        "password": "Init@1125!@#$.Password",
        "agreement": "click",
        "submit": "click"
      },
      "named_writes": {}
    },
    {
      "index": 4,
      "action": "wait",
      "model": "",
      "phase": "预处理",
      "status": "ok",
      "return_source": "keyword_result",
      "return_value": true,
      "named_writes": {}
    },
    {
      "index": 5,
      "action": "evaluate",
      "model": "",
      "phase": "用例",
      "status": "ok",
      "return_source": "evaluate",
      "return_value": {
        "caseId": "PROMO_ADD_COMBO_003",
        "activityName": "自动化-平台促销-组合-1778316185615-PROMO_ADD_COMBO_003",
        "time": {
          "start": "2026-05-09 16:43:05",
          "end": "2026-05-09 16:53:05"
        }
      },
      "named_writes": {}
    },
    {
      "index": 6,
      "action": "close",
      "model": "",
      "phase": "后处理",
      "status": "ok",
      "return_source": "keyword_result",
      "return_value": true,
      "named_writes": {}
    }
  ],
  "context_snapshot": {
    "named": {}
  }
}